loris/AMDStream.py
loris/ATISStream.py
loris/CSV.py
loris/ColorStream.py
loris/DAT.py
loris/DVSStream.py
loris/EventStream.py
loris/GenericStream.py
loris/ReadFile.py
loris/WriteEventsToFile.py
loris/__init__.py
loris/config.py
loris/readStream.py
loris/readtddat.py
loris-0.2.1.dist-info/LICENSE.txt
loris-0.2.1.dist-info/METADATA
loris-0.2.1.dist-info/WHEEL
loris-0.2.1.dist-info/top_level.txt
loris-0.2.1.dist-info/RECORD
