Metadata-Version: 2.1
Name: loris
Version: 0.2.1
Summary: read and write files from neuromorphic cameras
Home-page: https://github.com/neuromorphic-paris/loris
Author: Gregor Lenz
Author-email: gregor.lenz@inserm.fr
License: UNKNOWN
Platform: UNKNOWN
Classifier: Programming Language :: Python :: 3
Classifier: License :: OSI Approved :: GNU General Public License v3 (GPLv3)
Classifier: Operating System :: OS Independent
Requires-Dist: numpy
